eccpy/__init__.py
eccpy/compare_raw.py
eccpy/curvefit.py
eccpy/gather.py
eccpy/judgefit.py
eccpy/settings.py
eccpy/tools.py
eccpy/examples/example_data/generated_data_0.xlsx
eccpy/examples/example_data/generated_data_1.xlsx
eccpy/examples/example_data/generated_data_2.xlsx
eccpy/examples/example_settings/ECCpy_settings_template.xlsx
eccpy/examples/example_settings/eccpy-xlsx-generic-vertical_template.xlsx
test/__init__.py
test/helpers/__init__.py
test/helpers/helpers.py
eccpy-0.5.1.dist-info/METADATA
eccpy-0.5.1.dist-info/WHEEL
eccpy-0.5.1.dist-info/license.txt
eccpy-0.5.1.dist-info/top_level.txt
eccpy-0.5.1.dist-info/RECORD
