Metadata-Version: 2.1
Name: eccpy
Version: 0.5.1
Summary: High-throughput calculation of EC50 values.
Home-page: https://github.com/teese/eccpy
Author: Mark Teese
Author-email: mark.teese@checkthereadme.com
License: MIT
Download-URL: https://github.com/teese/eccpy/archive/0.5.1.tar.gz
Project-URL: Wiki, https://github.com/teese/eccpy/wiki
Project-URL: LangoschLab, http://cbp.wzw.tum.de/index.php?id=9
Project-URL: TU_Muenchen, https://www.tum.de
Project-URL: TNG Technology Consulting GmbH, https://www.tngtech.com/en/index.html
Keywords: EC50 LD50 IC50 doseresponse concentration dose inhibitor sigmoidal curve
Platform: UNKNOWN
Classifier: Intended Audience :: Science/Research
Classifier: License :: OSI Approved :: MIT License
Classifier: Programming Language :: Python :: 3
Classifier: Topic :: Scientific/Engineering :: Bio-Informatics
Classifier: Topic :: Scientific/Engineering :: Medical Science Apps.
Classifier: Topic :: Scientific/Engineering :: Chemistry
Requires-Dist: pandas
Requires-Dist: numpy
Requires-Dist: matplotlib
Requires-Dist: pytest
Requires-Dist: scipy
Requires-Dist: xlrd
Requires-Dist: openpyxl
